queue_status/__init__.py
queue_status/__main__.py
queue_status/main.py
queue_status-0.21.dist-info/DESCRIPTION.rst
queue_status-0.21.dist-info/METADATA
queue_status-0.21.dist-info/RECORD
queue_status-0.21.dist-info/WHEEL
queue_status-0.21.dist-info/metadata.json
queue_status-0.21.dist-info/pbr.json
queue_status-0.21.dist-info/top_level.txt
