Metadata-Version: 2.0
Name: queue-status
Version: 0.21
Summary: update a table in a database with status and time
Home-page: https://github.com/jeremiahsavage/queue_status
Author: Jeremiah H. Savage
Author-email: jeremiahsavage@gmail.com
License: Apache 2.0
Platform: UNKNOWN
Classifier: Development Status :: 3 - Alpha
Classifier: Intended Audience :: Developers
Classifier: License :: OSI Approved :: Apache Software License
Classifier: Programming Language :: Python
Classifier: Programming Language :: Python :: 2
Classifier: Programming Language :: Python :: 3
Requires-Dist: cdis-pipe-utils
Requires-Dist: pandas
Requires-Dist: sqlalchemy
